voice_agents/__init__.py
voice_agents/client.py
voice_agents/main.py
voice_agents/models_and_voices.py
voice_agents/speech_to_text.py
voice_agents/utils.py
voice_agents-0.2.0.dist-info/LICENSE
voice_agents-0.2.0.dist-info/METADATA
voice_agents-0.2.0.dist-info/WHEEL
voice_agents-0.2.0.dist-info/RECORD
