Metadata-Version: 2.3
Name: voice-agents
Version: 0.2.0
Summary: A comprehensive Python library for building production-ready voice agents with multi-provider support. Features real-time streaming TTS/STT, OpenAI, ElevenLabs, and Groq integration, audio processing, and seamless conversational AI capabilities.
License: MIT
Keywords: voice agents,voice ai,text-to-speech,speech-to-text,tts,stt,voice assistants,conversational ai,voice interfaces,audio processing,real-time streaming,streaming audio,openai,openai tts,openai api,groq,groq voice,elevenlabs,elevenlabs api,voice synthesis,speech synthesis,voice recognition,speech recognition,audio streaming,streaming tts,streaming stt,ai agents,artificial intelligence,llms,large language models,voice applications,voice bots,audio generation,multimodal ai,voice interaction,
Author: Kye Gomez
Author-email: kye@swarms.world
Requires-Python: >=3.10,<4.0
Classifier: Development Status :: 4 - Beta
Classifier: Intended Audience :: Developers
Classifier: License :: OSI Approved :: MIT License
Classifier: Programming Language :: Python :: 3
Classifier: Programming Language :: Python :: 3.10
Classifier: Programming Language :: Python :: 3.11
Classifier: Programming Language :: Python :: 3.12
Classifier: Programming Language :: Python :: 3.13
Classifier: Topic :: Scientific/Engineering :: Artificial Intelligence
Requires-Dist: httpcore[h2]
Requires-Dist: httpx
Requires-Dist: loguru
Requires-Dist: numpy
Requires-Dist: python-dotenv
Requires-Dist: setuptools
Requires-Dist: sounddevice
Requires-Dist: soundfile
Requires-Dist: websockets
Project-URL: Documentation, https://github.com/The-Swarm-Corporation/Voice-Agents
Project-URL: Homepage, https://github.com/The-Swarm-Corporation/Voice-Agents
Project-URL: Repository, https://github.com/The-Swarm-Corporation/Voice-Agents
